Test01.py
__init__.py
abdi_config.py
broker/__init__.py
broker/broker_maker.py
broker/empty_broker.py
broker/message_broker.py
broker/mqtt_broker.py
broker/notifier.py
broker/redis_broker.py
broker/ros_broker.py
broker/ros_noetic_broker.py
core/Agent.py
core/Belief.py
core/Desire.py
core/Intention.py
core/__init__.py
holon/Blackboard.py
holon/Heart.py
holon/HolonicAgent.py
holon/HolonicDesire.py
holon/HolonicIntention.py
holon/__init__.py
holon/payload.py
holon/payload_wrapper-20240106a.py
holon/payload_wrapper.py
holon/logistics/__init__.py
holon/logistics/base_logistic.py
holon/logistics/broker_logistic.py
holon/logistics/loading_coordinator.py
holon/logistics/payload_wrapper.py
holon/logistics/request_logistic.py
holon/logistics/response_logistic.py
agent_bdi-2.5.2.dist-info/LICENSE.md
agent_bdi-2.5.2.dist-info/METADATA
agent_bdi-2.5.2.dist-info/WHEEL
agent_bdi-2.5.2.dist-info/top_level.txt
agent_bdi-2.5.2.dist-info/RECORD
