Metadata-Version: 2.1
Name: agent-bdi
Version: 2.5.2
Summary: Agent BDI framework
Home-page: https://github.com/mfshiu/abdi.git
Author: Ming Fang Shiu
Author-email: avatar.xu@gmail.com
Project-URL: Bug Tracker, https://bugtracker.zoho.com/portal/avatardotxugmaildotcom#allprojects/1982079000000043717/
Classifier: Programming Language :: Python :: 3
Classifier: License :: OSI Approved :: MIT License
Classifier: Operating System :: OS Independent
Requires-Python: >=3.9
License-File: LICENSE.md
